<?xml version="1.0"?>
<record>
	<field id="7" value="Ankara, Ankara Ili, 陌c Anadolu"></field>
	<field id="5" value="Turkey"></field>
	<field id="19" value="Greek"></field>
	<field id="26" value="Fragment from the Res Gestae Inscription"></field>
	<field id="27" value="Fragment from the Res Gestae Divi Augusti inscription at Monumentum Ancyranum."></field>
	<field id="46" value="螘螡违螤螒韦螘螜螒螜螘螝韦螚螜螝螒螜螘螔螖螣螠螚螜螠螘韦螒韦螣韦螣违危螘螠桅违 / 螞螜螣违危螙螔螘螙螒螜螠螘螤螣螞螘螠螣违危螝螒韦螒韦螒危螘违围螒危韦惟螡螘 / 螠惟螡螤螣螞螘[螜]韦惟螡螘螡螝巍螒韦螚危桅螘螡螣螠螘螡螣危螤螒螡韦惟螡韦惟螡 / 螤巍螒螕螠螒韦惟螡螘螝韦螚危螘螠螚危螘螢螣违危螜螒危螘螜危韦螚螡韦螚危危违螡 / 螝螞螚韦螣违螝螒螜韦螣违螖螚螠螣违韦惟螡巍[惟]螠螒螜惟螡螠螘韦螚螡螘螕螝螒 / 螝违巍螜螚螒螡螘螢螚危螒螜韦螜螒危螖螣螕螠螒韦螜危违螡螝螞螚韦螣违危螘螔螒危韦螣危 / 螤巍螣危[螚螕螣巍螘]违螛螚螡螝螒螜螖螒桅螡螒螜危螖螚螠螣危螜螒螜韦螒螤巍螣螤违 / 螞螒[螠螣违螘危韦螘桅螛]螚螣韦螘螖巍违螜螡螣危危韦螘桅螒螡螣危螣螖螜螖螣螠螘螡螣危"></field>
</record>