<?xml version="1.0"?>
<record>
	<field id="7" value="Ankara, Ankara Ili, 陌c Anadolu"></field>
	<field id="5" value="Turkey"></field>
	<field id="19" value="Greek"></field>
	<field id="26" value="Fragment from the Res Gestae Inscription"></field>
	<field id="27" value="Fragment from the Res Gestae Divi Augusti inscription at Monumentum Ancyranum."></field>
	<field id="46" value="螘螤螜危惟韦螚巍螜螒螜韦惟螡螤螣螞螘螜韦惟螡违螤螘巍螒[螡]惟韦螣违螤违螞惟 / 螡螣危韦螚危螘螠螚危螣螜螝螜螒危螒螡螒韦螘螛螚  螣螤[螞螣螡]韦螘围巍违 / 危螣违螡螘螡韦惟螜螔螣[违]螞螘违韦螚巍螜惟螜螒螡螒韦螘螛[螘]螡违螤螣韦螘韦螚危 / 危违螡螝螞螚韦螣违螝螒螜韦螣违螖螚螠螣违韦惟螡巍惟螠[螒]螜惟螡螖螜螒韦螚危 / 螘螤螜螕巍螒桅螚危螒巍螘韦螚螡螝螒螜螘螤螘螜螝螘螜螒螡螝螒[螜螖]螜螝螒螜螣危违螡螚螡 /螝螒螜螘违危螘螔螘螜螒螡螘螠螣螜螠螒巍韦违巍螘螜  螒螢惟螠[螒]韦螜  螤螒螡韦惟螡 / 螖螜螚螡螘螕螝螒螘螢螣违危螜螒危螖螘螣违螖螘螡韦螜螤螞螘螜螣螡螘危围螣螡 / 韦惟螡危违螡螒巍螢螒螡韦惟螡螠螣螜 / 韦巍螜危螝螒螜螖螘螝螒韦螚螡违螤螒韦螘螜螒螡螒螕螣螡韦螣危螠螣违螚韦螘危违螡"></field>
</record>